{
  "info": {
    "name": "System Integrations Compolsory Assignment 01",
    "schema": "https://schema.getpostman.com/json/collection/v2.1.0/collection.json"
  },
  "item": [
    {
      "name": "Get Users",
      "event": [],
      "request": {
        "method": "GET",
        "header": [],
        "auth": null,
        "description": "",
        "url": {
          "raw": "http://localhost:8080/api/Users",
          "protocol": "http",
          "host": [
            "localhost:8080"
          ],
          "path": [
            "api",
            "Users"
          ],
          "query": [],
          "variable": []
        }
      }
    },
    {
      "name": "Add User",
      "event": [],
      "request": {
        "method": "POST",
        "header": [],
        "auth": null,
        "description": "",
        "url": {
          "raw": "http://localhost:8080/api/Users",
          "protocol": "http",
          "host": [
            "localhost:8080"
          ],
          "path": [
            "api",
            "Users"
          ],
          "query": [],
          "variable": []
        },
        "body": {
          "mode": "raw",
          "raw": "{\n  \"UserId\": 100,\n  \"UserName\": \"Svend Bent\"\n}",
          "options": {
            "raw": {
              "language": "json"
            }
          }
        }
      }
    },
    {
      "name": "Get Tweets",
      "event": [],
      "request": {
        "method": "GET",
        "header": [],
        "auth": null,
        "description": "",
        "url": {
          "raw": "http://localhost:8081/api/Tweets",
          "protocol": "http",
          "host": [
            "localhost:8081"
          ],
          "path": [
            "api",
            "Tweets"
          ],
          "query": [],
          "variable": []
        }
      }
    },
    {
      "name": "Tweet",
      "event": [],
      "request": {
        "method": "POST",
        "header": [],
        "auth": null,
        "description": "",
        "url": {
          "raw": "http://localhost:8081/api/Tweets",
          "protocol": "http",
          "host": [
            "localhost:8081"
          ],
          "path": [
            "api",
            "Tweets"
          ],
          "query": [],
          "variable": []
        },
        "body": {
          "mode": "raw",
          "raw": "{\n  \"TweetID\":10,\n  \"TweetText\": \"Awesome Tweet right here!!!\"\n}",
          "options": {
            "raw": {
              "language": "json"
            }
          }
        }
      }
    }
  ],
  "variable": []
}